detadantic/__init__.py
detadantic-0.0.11.dist-info/LICENSE
detadantic-0.0.11.dist-info/METADATA
detadantic-0.0.11.dist-info/WHEEL
detadantic-0.0.11.dist-info/top_level.txt
detadantic-0.0.11.dist-info/RECORD
